[
  {
    "ContainingType": "SalesController",
    "Method": "AddSale",
    "RelativePath": "add",
    "HttpMethod": "POST",
    "IsController": true,
    "Order": 0,
    "Parameters": [
      {
        "Name": "saleDto",
        "Type": "CarFactory.DTOs.AddSaleDto",
        "IsRequired": true
      }
    ],
    "ReturnTypes": [
      {
        "Type": "System.Void",
        "MediaTypes": [],
        "StatusCode": 201
      },
      {
        "Type": "System.Void",
        "MediaTypes": [],
        "StatusCode": 400
      }
    ]
  },
  {
    "ContainingType": "CarFactory.Controllers.CarTypeController",
    "Method": "GetSalePercentageByModel",
    "RelativePath": "price/{carType}",
    "HttpMethod": "GET",
    "IsController": true,
    "Order": 0,
    "Parameters": [
      {
        "Name": "carType",
        "Type": "System.String",
        "IsRequired": true
      }
    ],
    "ReturnTypes": [
      {
        "Type": "System.Void",
        "MediaTypes": [],
        "StatusCode": 200
      }
    ]
  },
  {
    "ContainingType": "SalesController",
    "Method": "GetSalesByDistributionCenter",
    "RelativePath": "sales-by-center/{centerName}",
    "HttpMethod": "GET",
    "IsController": true,
    "Order": 0,
    "Parameters": [
      {
        "Name": "centerName",
        "Type": "System.String",
        "IsRequired": true
      }
    ],
    "ReturnTypes": [
      {
        "Type": "System.Void",
        "MediaTypes": [],
        "StatusCode": 200
      }
    ]
  },
  {
    "ContainingType": "SalesController",
    "Method": "GetSalePercentageByModel",
    "RelativePath": "sales-percentage/{carType}/{center}",
    "HttpMethod": "GET",
    "IsController": true,
    "Order": 0,
    "Parameters": [
      {
        "Name": "carType",
        "Type": "",
        "IsRequired": true
      },
      {
        "Name": "center",
        "Type": "",
        "IsRequired": true
      }
    ],
    "ReturnTypes": [
      {
        "Type": "System.Void",
        "MediaTypes": [],
        "StatusCode": 200
      }
    ]
  },
  {
    "ContainingType": "SalesController",
    "Method": "GetTotalSalesVolume",
    "RelativePath": "total-sales-volume",
    "HttpMethod": "GET",
    "IsController": true,
    "Order": 0,
    "Parameters": [],
    "ReturnTypes": [
      {
        "Type": "System.Void",
        "MediaTypes": [],
        "StatusCode": 200
      }
    ]
  }
]